ovf/__init__.py
ovf/ovf.py
ovf/ovflib.py
ovf-0.4.3.dist-info/LICENSE.txt
ovf-0.4.3.dist-info/METADATA
ovf-0.4.3.dist-info/WHEEL
ovf-0.4.3.dist-info/top_level.txt
ovf-0.4.3.dist-info/RECORD
