Metadata-Version: 2.1
Name: ovf
Version: 0.4.3
Summary: OVF file parser
Home-page: https://github.com/spirit-code/ovf
Author: Gideon Mueller
Author-email: g.mueller@fz-juelich.de
Maintainer: Gideon Mueller
Maintainer-email: g.mueller@fz-juelich.de
License: MIT
Keywords: OVF,parser
Platform: UNKNOWN
Classifier: Development Status :: 4 - Beta
Classifier: Intended Audience :: Science/Research
Classifier: Natural Language :: English
Classifier: License :: OSI Approved :: MIT License
Classifier: Operating System :: OS Independent
Classifier: Programming Language :: C
Classifier: Programming Language :: C++
Classifier: Programming Language :: Python
Classifier: Topic :: Scientific/Engineering
Classifier: Topic :: Software Development :: Libraries :: Python Modules
Requires-Dist: numpy
